{
  "tafsirs": [
    {
      "verse_id": 1,
      "isHTML": true,
      "isTafsir": true,
      "text": "ألم تعلم -أيها الرسول- كيف فعل ربك بأصحاب الفيل: أبرهة الحبشي وجيشه الذين أرادوا تدمير الكعبة المباركة؟"
    },
    {
      "verse_id": 2,
      "isHTML": true,
      "isTafsir": true,
      "text": "ألم يجعل ما دبَّروه من شر في إبطال وتضييع؟"
    },
    {
      "verse_id": 3,
      "isHTML": true,
      "isTafsir": true,
      "text": "وبعث عليهم طيرًا في جماعات متتابعة، تقذفهم بحجارة من طين متحجِّر."
    },
    {
      "verse_id": 4,
      "isHTML": true,
      "isTafsir": true,
      "text": "وبعث عليهم طيرًا في جماعات متتابعة، تقذفهم بحجارة من طين متحجِّر."
    },
    {
      "verse_id": 5,
      "isHTML": true,
      "isTafsir": true,
      "text": "فجعلهم به محطمين كأوراق الزرع اليابسة التي أكلتها البهائم ثم رمت بها."
    }
  ]
}
